llmxml/__init__.py
llmxml/parser.py
llmxml/patch.py
llmxml/prompting.py
llmxml/prompts.py
llmxml-0.4.4.dist-info/LICENSE
llmxml-0.4.4.dist-info/METADATA
llmxml-0.4.4.dist-info/WHEEL
llmxml-0.4.4.dist-info/top_level.txt
llmxml-0.4.4.dist-info/RECORD
