Metadata-Version: 2.1
Name: llmxml
Version: 0.4.4
Summary: XML parsing for LLM outputs
Requires-Python: >=3.12
License-File: LICENSE
Requires-Dist: partialjson>=0.0.8
Requires-Dist: pydantic>=2.10.2
